pytest_opentmi/OpenTmiReport.py
pytest_opentmi/__init__.py
pytest_opentmi/plugin.py
pytest_opentmi-0.5.2.dist-info/LICENSE
pytest_opentmi-0.5.2.dist-info/METADATA
pytest_opentmi-0.5.2.dist-info/WHEEL
pytest_opentmi-0.5.2.dist-info/entry_points.txt
pytest_opentmi-0.5.2.dist-info/top_level.txt
pytest_opentmi-0.5.2.dist-info/RECORD
