Metadata-Version: 2.1
Name: pytest-opentmi
Version: 0.5.2
Summary: pytest plugin for publish results to opentmi
Home-page: https://github.com/opentmi/pytest-opentmi
Author: Jussi Vatjus-Anttila
Author-email: jussiva@gmail.com
License: Mozilla Public License 2.0 (MPL 2.0)
Keywords: py.test pytest opentmi report
Classifier: Development Status :: 5 - Production/Stable
Classifier: Framework :: Pytest
Classifier: Intended Audience :: Developers
Classifier: License :: OSI Approved :: Mozilla Public License 2.0 (MPL 2.0)
Classifier: Operating System :: POSIX
Classifier: Operating System :: Microsoft :: Windows
Classifier: Operating System :: MacOS :: MacOS X
Classifier: Topic :: Software Development :: Quality Assurance
Classifier: Topic :: Software Development :: Testing
Classifier: Topic :: Utilities
Classifier: Programming Language :: Python
Classifier: Programming Language :: Python :: 3
Classifier: Programming Language :: Python :: 3.8
Classifier: Programming Language :: Python :: 3.9
Classifier: Programming Language :: Python :: 3.10
Classifier: Programming Language :: Python :: 3.11
Classifier: Programming Language :: Python :: 3 :: Only
Requires-Python: >=3.6
License-File: LICENSE
Requires-Dist: pytest>=5.0
Requires-Dist: pytest-metadata
Requires-Dist: opentmi-client>=0.10.1
Requires-Dist: joblib
Provides-Extra: dev
Requires-Dist: coverage; extra == "dev"
Requires-Dist: coveralls; extra == "dev"
Requires-Dist: mock; extra == "dev"
Requires-Dist: pylint==2.15.10; extra == "dev"
Requires-Dist: pynose; extra == "dev"
Requires-Dist: pyinstaller; extra == "dev"
